<?xml version="1.0" encoding="UTF-8"?>
<objects serializationModel="Studio.01.10.00">
    <object class="AudioFile" id="{6bf56ab9-6352-4c04-b031-5c8992a7f456}">
        <property name="assetPath">
            <value>Skill/翻开.ogg</value>
        </property>
        <property name="frequencyInKHz">
            <value>64</value>
        </property>
        <property name="channelCount">
            <value>1</value>
        </property>
        <property name="length">
            <value>1.0153593750000001</value>
        </property>
        <relationship name="masterAssetFolder">
            <destination>{992e23d0-0fbd-4420-a7dc-e0805394bcec}</destination>
        </relationship>
    </object>
</objects>
